pkulaw_mcp_proxy/__init__.py
pkulaw_mcp_proxy/__main__.py
pkulaw_mcp_proxy/proxy.py
pkulaw_mcp_proxy-0.2.1.dist-info/METADATA
pkulaw_mcp_proxy-0.2.1.dist-info/WHEEL
pkulaw_mcp_proxy-0.2.1.dist-info/entry_points.txt
pkulaw_mcp_proxy-0.2.1.dist-info/RECORD
