Metadata-Version: 2.4
Name: pkulaw-mcp-proxy
Version: 0.2.1
Summary: PKULAW MCP server proxy
Author-email: PKULAW <fxtj@chinalawinfo.com>
License-Expression: MIT
Keywords: MCP server,PKULAW,proxy
Classifier: Development Status :: 4 - Beta
Classifier: Intended Audience :: Developers
Classifier: License :: OSI Approved :: MIT License
Classifier: Operating System :: OS Independent
Classifier: Programming Language :: Python :: 3
Classifier: Programming Language :: Python :: 3.10
Requires-Python: >=3.10
Requires-Dist: fastmcp>=2.10.5
